zstandard/__init__.py
zstandard/__init__.pyi
zstandard/_cffi.cpython-312.so
zstandard/backend_c.cpython-312.so
zstandard/backend_cffi.py
zstandard/py.typed
zstandard_qpython-0.23.0.dist-info/METADATA
zstandard_qpython-0.23.0.dist-info/WHEEL
zstandard_qpython-0.23.0.dist-info/top_level.txt
zstandard_qpython-0.23.0.dist-info/RECORD
