Metadata-Version: 2.4
Name: zstandard-qpython
Version: 0.23.0
Summary: Zstandard bindings for Python
Author-email: The QPYPI Team <qpypi@qpython.org>
License: MIT AND (Apache-2.0 OR BSD-2-Clause)
Project-URL: Homepage, https://qpypi.qpython.org/project/zstandard-qpython/
Classifier: Intended Audience :: Developers
Classifier: Intended Audience :: Education
Classifier: Intended Audience :: Information Technology
Classifier: Intended Audience :: End Users/Desktop
Classifier: License :: OSI Approved :: Apache Software License
Classifier: Operating System :: Android
Classifier: Programming Language :: Python
Classifier: Programming Language :: Python :: 3.12
Classifier: Topic :: Software Development
Requires-Python: ==3.12.*
